serializable/__init__.py
serializable/formatters.py
serializable/helpers.py
serializable/py.typed
py_serializable-1.0.1.dist-info/LICENSE
py_serializable-1.0.1.dist-info/METADATA
py_serializable-1.0.1.dist-info/WHEEL
py_serializable-1.0.1.dist-info/RECORD
