Metadata-Version: 2.1
Name: py-serializable
Version: 1.0.1
Summary: Library for serializing and deserializing Python Objects to and from JSON and XML.
Home-page: https://github.com/madpah/serializable#readme
License: Apache-2.0
Keywords: serialization,deserialization,JSON,XML
Author: Paul Horton
Author-email: paul.horton@owasp.org
Maintainer: Jan Kowalleck
Maintainer-email: jan.kowalleck@gmail.com
Requires-Python: >=3.8,<4.0
Classifier: Development Status :: 5 - Production/Stable
Classifier: Intended Audience :: Developers
Classifier: Intended Audience :: Information Technology
Classifier: License :: OSI Approved :: Apache Software License
Classifier: Programming Language :: Python :: 3
Classifier: Programming Language :: Python :: 3.8
Classifier: Programming Language :: Python :: 3.9
Classifier: Programming Language :: Python :: 3.10
Classifier: Programming Language :: Python :: 3.11
Classifier: Programming Language :: Python :: 3.12
Classifier: Topic :: Software Development
Classifier: Typing :: Typed
Requires-Dist: defusedxml (>=0.7.1,<0.8.0)
Project-URL: Bug Tracker, https://github.com/madpah/serializable/issues
Project-URL: Documentation, https://py-serializable.readthedocs.io/
Project-URL: Repository, https://github.com/madpah/serializable
